smsframework_pswin/__init__.py
smsframework_pswin/api.py
smsframework_pswin/error.py
smsframework_pswin/provider.py
smsframework_pswin/receiver.py
smsframework_pswin/status.py
smsframework_pswin-0.3.4.dist-info/LICENSE
smsframework_pswin-0.3.4.dist-info/METADATA
smsframework_pswin-0.3.4.dist-info/WHEEL
smsframework_pswin-0.3.4.dist-info/top_level.txt
smsframework_pswin-0.3.4.dist-info/RECORD
