Metadata-Version: 2.1
Name: smsframework-pswin
Version: 0.3.4
Summary: SMS framework: PSWin provider 
Home-page: https://github.com/dignio/py-smsframework-pswin
Author: Dignio
License: MIT
Keywords: sms,message,notification,receive,send,pswin
Platform: any
Classifier: Development Status :: 5 - Production/Stable
Classifier: Intended Audience :: Developers
Classifier: Natural Language :: English
Classifier: Programming Language :: Python :: 2
Classifier: Programming Language :: Python :: 3
Classifier: Operating System :: OS Independent
Requires-Dist: smsframework (>=0.0.9)
Requires-Dist: requests (>=2.4.3)
Provides-Extra: receiver
Requires-Dist: flask (>=0.10) ; extra == 'receiver'
